vocabs/__init__.py
vocabs/admin.py
vocabs/api_views.py
vocabs/apps.py
vocabs/custom_layout_object.py
vocabs/dal_urls.py
vocabs/dal_views.py
vocabs/endpoints.py
vocabs/filters.py
vocabs/forms.py
vocabs/models.py
vocabs/rdf_utils.py
vocabs/serializers.py
vocabs/skos_import.py
vocabs/tables.py
vocabs/urls.py
vocabs/views.py
vocabs/migrations/0001_initial.py
vocabs/migrations/__init__.py
vocabs/templates/vocabs/formset.html
vocabs/templates/vocabs/formset_row.html
vocabs/templates/vocabs/skoscollection_detail.html
vocabs/templates/vocabs/skosconcept_detail.html
vocabs/templates/vocabs/skosconceptscheme_detail.html
vocabs/templates/vocabs/upload.html
vocabs/test_utils/__init__.py
vocabs/test_utils/test_app/__init__.py
vocabs/test_utils/test_app/admin.py
vocabs/test_utils/test_app/apps.py
vocabs/test_utils/test_app/models.py
vocabs/test_utils/test_app/migrations/__init__.py
vocabs/tests/__init__.py
vocabs/tests/constants.py
vocabs/tests/test_import_export.py
vocabs/tests/test_models.py
acdh_django_vocabs-1.1.1.dist-info/AUTHORS.rst
acdh_django_vocabs-1.1.1.dist-info/LICENSE
acdh_django_vocabs-1.1.1.dist-info/METADATA
acdh_django_vocabs-1.1.1.dist-info/WHEEL
acdh_django_vocabs-1.1.1.dist-info/top_level.txt
acdh_django_vocabs-1.1.1.dist-info/RECORD
