Metadata-Version: 2.1
Name: acdh-django-vocabs
Version: 1.1.1
Summary: Curate controlled vocabularies as SKOS
Home-page: https://github.com/acdh-oeaw/acdh-django-vocabs
Author: Peter Andorfer
Author-email: peter.andorfer@oeaw.ac.at
License: MIT
Keywords: acdh-django-vocabs
Platform: UNKNOWN
Classifier: Development Status :: 3 - Alpha
Classifier: Framework :: Django :: 3.1
Classifier: Intended Audience :: Developers
Classifier: License :: OSI Approved :: BSD License
Classifier: Natural Language :: English
Classifier: Programming Language :: Python :: 3
Classifier: Programming Language :: Python :: 3.7
Classifier: Programming Language :: Python :: 3.8
License-File: LICENSE
License-File: AUTHORS.rst
Requires-Dist: acdh-django-browsing>=0.2.0
Requires-Dist: django-mptt<1,>=0.11.0
Requires-Dist: django-reversion<6,>=3.0.8
Requires-Dist: djangorestframework<4,>=3.12.2
Requires-Dist: rdflib<7,>=5.0.0
